<?xml version="1.0" encoding="US-ASCII" standalone="yes"?><?mso-application progid="Excel.Sheet"?><Workbook xmlns="urn:schemas-microsoft-com:office:spreadsheet" xmlns:o="urn:schemas-microsoft-com:office:office" xmlns:x="urn:schemas-microsoft-com:office:excel" xmlns:ss="urn:schemas-microsoft-com:office:spreadsheet" xmlns:html="http://www.w3.org/TR/REC-html40"><DocumentProperties xmlns="urn:schemas-microsoft-com:office:office"><Author></Author><LastAuthor></LastAuthor><Created></Created><LastSaved></LastSaved><Company></Company><Version></Version></DocumentProperties><ExcelWorkbook  xmlns="urn:schemas-microsoft-com:office:excel"><ProtectStructure>False</ProtectStructure><ProtectWindows>False</ProtectWindows></ExcelWorkbook><Styles><Style ss:ID="Default" ss:Name="Normal"><Alignment ss:Vertical="Bottom"/><Borders/><Font ss:FontName="Calibri" ss:Size="10"/><Interior/><NumberFormat/><Protection/></Style><Style ss:ID="s1"><Font ss:FontName="Calibri" ss:Bold="1" ss:Size="12"/><NumberFormat/></Style><Style ss:ID="s21"><Alignment ss:Horizontal="Center" ss:Vertical="Bottom"/><NumberFormat/><Font ss:FontName="Calibri" ss:Size="10"/><Borders><Border ss:Position="Top" ss:LineStyle="Continuous" ss:Weight="1"/></Borders></Style><Style ss:ID="s22"><Alignment ss:Horizontal="Center" ss:Vertical="Bottom"/><Font ss:FontName="Calibri" ss:Size="10"/><NumberFormat/></Style><Style ss:ID="s23"><Alignment ss:Horizontal="Center" ss:Vertical="Bottom"/><NumberFormat/><Font ss:FontName="Calibri" ss:Size="10"/><Borders><Border ss:Position="Bottom" ss:LineStyle="Continuous" ss:Weight="1"/></Borders></Style><Style ss:ID="s24"><Font ss:FontName="Calibri" ss:Size="10"/><NumberFormat/></Style><Style ss:ID="s31"><Font ss:FontName="Calibri" ss:Size="10"/><Borders><Border ss:Position="Top" ss:LineStyle="Continuous" ss:Weight="1"/></Borders></Style><Style ss:ID="s32"><Font ss:FontName="Calibri" ss:Size="10"/><Borders/></Style><Style ss:ID="s33"><Font ss:FontName="Calibri" ss:Size="10"/><Borders><Border ss:Position="Bottom" ss:LineStyle="Continuous" ss:Weight="1"/></Borders></Style></Styles><Names></Names><Worksheet ss:Name="Sheet1"><Table ss:ExpandedColumnCount="11" ss:ExpandedRowCount="64" x:FullColumns="1" x:FullRows="1"><Column ss:AutoFitWidth="0" ss:Width="108"/><Column ss:AutoFitWidth="0" ss:Width="58"/><Column ss:AutoFitWidth="0" ss:Width="58"/><Column ss:AutoFitWidth="0" ss:Width="58"/><Column ss:AutoFitWidth="0" ss:Width="58"/><Column ss:AutoFitWidth="0" ss:Width="58"/><Column ss:AutoFitWidth="0" ss:Width="58"/><Column ss:AutoFitWidth="0" ss:Width="58"/><Column ss:AutoFitWidth="0" ss:Width="58"/><Column ss:AutoFitWidth="0" ss:Width="58"/><Column ss:AutoFitWidth="0" ss:Width="58"/><Row></Row><Row><Cell ss:StyleID="s31"><Data ss:Type="String"></Data></Cell><Cell ss:StyleID="s21"><Data ss:Type="String">(1)</Data></Cell><Cell ss:StyleID="s21"><Data ss:Type="String">(2)</Data></Cell><Cell ss:StyleID="s21"><Data ss:Type="String">(3)</Data></Cell><Cell ss:StyleID="s21"><Data ss:Type="String">(4)</Data></Cell><Cell ss:StyleID="s21"><Data ss:Type="String">(5)</Data></Cell><Cell ss:StyleID="s21"><Data ss:Type="String">(6)</Data></Cell><Cell ss:StyleID="s21"><Data ss:Type="String">(7)</Data></Cell><Cell ss:StyleID="s21"><Data ss:Type="String">(8)</Data></Cell><Cell ss:StyleID="s21"><Data ss:Type="String">(9)</Data></Cell><Cell ss:StyleID="s21"><Data ss:Type="String">(10)</Data></Cell></Row><Row><Cell ss:StyleID="s32"><Data ss:Type="String">VARIABLES</Data></Cell><Cell ss:StyleID="s22"><Data ss:Type="String">OLS</Data></Cell><Cell ss:StyleID="s22"><Data ss:Type="String">IV</Data></Cell><Cell ss:StyleID="s22"><Data ss:Type="String">CF</Data></Cell><Cell ss:StyleID="s22"><Data ss:Type="String">OLS</Data></Cell><Cell ss:StyleID="s22"><Data ss:Type="String">PSM</Data></Cell><Cell ss:StyleID="s22"><Data ss:Type="String">PSM2</Data></Cell><Cell ss:StyleID="s22"><Data ss:Type="String">OLS</Data></Cell><Cell ss:StyleID="s22"><Data ss:Type="String">DiD Pr</Data></Cell><Cell ss:StyleID="s22"><Data ss:Type="String">OLS</Data></Cell><Cell ss:StyleID="s22"><Data ss:Type="String">DiD Pd</Data></Cell></Row><Row><Cell ss:StyleID="s31"><Data ss:Type="String"></Data></Cell><Cell ss:StyleID="s21"><Data ss:Type="String"></Data></Cell><Cell ss:StyleID="s21"><Data ss:Type="String"></Data></Cell><Cell ss:StyleID="s21"><Data ss:Type="String"></Data></Cell><Cell ss:StyleID="s21"><Data ss:Type="String"></Data></Cell><Cell ss:StyleID="s21"><Data ss:Type="String"></Data></Cell><Cell ss:StyleID="s21"><Data ss:Type="String"></Data></Cell><Cell ss:StyleID="s21"><Data ss:Type="String"></Data></Cell><Cell ss:StyleID="s21"><Data ss:Type="String"></Data></Cell><Cell ss:StyleID="s21"><Data ss:Type="String"></Data></Cell><Cell ss:StyleID="s21"><Data ss:Type="String"></Data></Cell></Row><Row><Cell ss:StyleID="s32"><Data ss:Type="String">ReggioMaterna</Data></Cell><Cell ss:StyleID="s22"><Data ss:Type="String">-0.402</Data></Cell><Cell ss:StyleID="s22"><Data ss:Type="String">-0.356</Data></Cell><Cell ss:StyleID="s22"><Data ss:Type="String">1.338</Data></Cell><Cell ss:StyleID="s22"><Data ss:Type="String">-1.059</Data></Cell><Cell ss:StyleID="s22"><Data ss:Type="String">-0.802</Data></Cell><Cell ss:StyleID="s22"><Data ss:Type="String">-1.051</Data></Cell><Cell ss:StyleID="s22"><Data ss:Type="String">-0.386</Data></Cell><Cell ss:StyleID="s22"><Data ss:Type="String">-1.403</Data></Cell><Cell ss:StyleID="s22"><Data ss:Type="String">-0.508</Data></Cell><Cell ss:StyleID="s22"><Data ss:Type="String">-0.145</Data></Cell></Row><Row><Cell ss:StyleID="s32"><Data ss:Type="String"></Data></Cell><Cell ss:StyleID="s22"><Data ss:Type="String">[0.820]</Data></Cell><Cell ss:StyleID="s22"><Data ss:Type="String">[3.923]</Data></Cell><Cell ss:StyleID="s22"><Data ss:Type="String">[4.932]</Data></Cell><Cell ss:StyleID="s22"><Data ss:Type="String">[0.657]</Data></Cell><Cell ss:StyleID="s22"><Data ss:Type="String">[0.669]</Data></Cell><Cell ss:StyleID="s22"><Data ss:Type="String">[0.658]</Data></Cell><Cell ss:StyleID="s22"><Data ss:Type="String">[0.803]</Data></Cell><Cell ss:StyleID="s22"><Data ss:Type="String">[1.220]</Data></Cell><Cell ss:StyleID="s22"><Data ss:Type="String">[0.805]</Data></Cell><Cell ss:StyleID="s22"><Data ss:Type="String">[1.225]</Data></Cell></Row><Row><Cell ss:StyleID="s32"><Data ss:Type="String">unobs</Data></Cell><Cell ss:StyleID="s22"><Data ss:Type="String"></Data></Cell><Cell ss:StyleID="s22"><Data ss:Type="String"></Data></Cell><Cell ss:StyleID="s22"><Data ss:Type="String">-3.331</Data></Cell><Cell ss:StyleID="s22"><Data ss:Type="String"></Data></Cell><Cell ss:StyleID="s22"><Data ss:Type="String"></Data></Cell><Cell ss:StyleID="s22"><Data ss:Type="String"></Data></Cell><Cell ss:StyleID="s22"><Data ss:Type="String"></Data></Cell><Cell ss:StyleID="s22"><Data ss:Type="String"></Data></Cell><Cell ss:StyleID="s22"><Data ss:Type="String"></Data></Cell><Cell ss:StyleID="s22"><Data ss:Type="String"></Data></Cell></Row><Row><Cell ss:StyleID="s32"><Data ss:Type="String"></Data></Cell><Cell ss:StyleID="s22"><Data ss:Type="String"></Data></Cell><Cell ss:StyleID="s22"><Data ss:Type="String"></Data></Cell><Cell ss:StyleID="s22"><Data ss:Type="String">[7.298]</Data></Cell><Cell ss:StyleID="s22"><Data ss:Type="String"></Data></Cell><Cell ss:StyleID="s22"><Data ss:Type="String"></Data></Cell><Cell ss:StyleID="s22"><Data ss:Type="String"></Data></Cell><Cell ss:StyleID="s22"><Data ss:Type="String"></Data></Cell><Cell ss:StyleID="s22"><Data ss:Type="String"></Data></Cell><Cell ss:StyleID="s22"><Data ss:Type="String"></Data></Cell><Cell ss:StyleID="s22"><Data ss:Type="String"></Data></Cell></Row><Row><Cell ss:StyleID="s32"><Data ss:Type="String">unobs2</Data></Cell><Cell ss:StyleID="s22"><Data ss:Type="String"></Data></Cell><Cell ss:StyleID="s22"><Data ss:Type="String"></Data></Cell><Cell ss:StyleID="s22"><Data ss:Type="String">3.296</Data></Cell><Cell ss:StyleID="s22"><Data ss:Type="String"></Data></Cell><Cell ss:StyleID="s22"><Data ss:Type="String"></Data></Cell><Cell ss:StyleID="s22"><Data ss:Type="String"></Data></Cell><Cell ss:StyleID="s22"><Data ss:Type="String"></Data></Cell><Cell ss:StyleID="s22"><Data ss:Type="String"></Data></Cell><Cell ss:StyleID="s22"><Data ss:Type="String"></Data></Cell><Cell ss:StyleID="s22"><Data ss:Type="String"></Data></Cell></Row><Row><Cell ss:StyleID="s32"><Data ss:Type="String"></Data></Cell><Cell ss:StyleID="s22"><Data ss:Type="String"></Data></Cell><Cell ss:StyleID="s22"><Data ss:Type="String"></Data></Cell><Cell ss:StyleID="s22"><Data ss:Type="String">[3.294]</Data></Cell><Cell ss:StyleID="s22"><Data ss:Type="String"></Data></Cell><Cell ss:StyleID="s22"><Data ss:Type="String"></Data></Cell><Cell ss:StyleID="s22"><Data ss:Type="String"></Data></Cell><Cell ss:StyleID="s22"><Data ss:Type="String"></Data></Cell><Cell ss:StyleID="s22"><Data ss:Type="String"></Data></Cell><Cell ss:StyleID="s22"><Data ss:Type="String"></Data></Cell><Cell ss:StyleID="s22"><Data ss:Type="String"></Data></Cell></Row><Row><Cell ss:StyleID="s32"><Data ss:Type="String">unobs3</Data></Cell><Cell ss:StyleID="s22"><Data ss:Type="String"></Data></Cell><Cell ss:StyleID="s22"><Data ss:Type="String"></Data></Cell><Cell ss:StyleID="s22"><Data ss:Type="String">5.777</Data></Cell><Cell ss:StyleID="s22"><Data ss:Type="String"></Data></Cell><Cell ss:StyleID="s22"><Data ss:Type="String"></Data></Cell><Cell ss:StyleID="s22"><Data ss:Type="String"></Data></Cell><Cell ss:StyleID="s22"><Data ss:Type="String"></Data></Cell><Cell ss:StyleID="s22"><Data ss:Type="String"></Data></Cell><Cell ss:StyleID="s22"><Data ss:Type="String"></Data></Cell><Cell ss:StyleID="s22"><Data ss:Type="String"></Data></Cell></Row><Row><Cell ss:StyleID="s32"><Data ss:Type="String"></Data></Cell><Cell ss:StyleID="s22"><Data ss:Type="String"></Data></Cell><Cell ss:StyleID="s22"><Data ss:Type="String"></Data></Cell><Cell ss:StyleID="s22"><Data ss:Type="String">[10.031]</Data></Cell><Cell ss:StyleID="s22"><Data ss:Type="String"></Data></Cell><Cell ss:StyleID="s22"><Data ss:Type="String"></Data></Cell><Cell ss:StyleID="s22"><Data ss:Type="String"></Data></Cell><Cell ss:StyleID="s22"><Data ss:Type="String"></Data></Cell><Cell ss:StyleID="s22"><Data ss:Type="String"></Data></Cell><Cell ss:StyleID="s22"><Data ss:Type="String"></Data></Cell><Cell ss:StyleID="s22"><Data ss:Type="String"></Data></Cell></Row><Row><Cell ss:StyleID="s32"><Data ss:Type="String">Age</Data></Cell><Cell ss:StyleID="s22"><Data ss:Type="String">0.023</Data></Cell><Cell ss:StyleID="s22"><Data ss:Type="String">0.026</Data></Cell><Cell ss:StyleID="s22"><Data ss:Type="String">0.118</Data></Cell><Cell ss:StyleID="s22"><Data ss:Type="String">1.018</Data></Cell><Cell ss:StyleID="s22"><Data ss:Type="String">0.708</Data></Cell><Cell ss:StyleID="s22"><Data ss:Type="String">1.114</Data></Cell><Cell ss:StyleID="s22"><Data ss:Type="String">0.300</Data></Cell><Cell ss:StyleID="s22"><Data ss:Type="String">0.415</Data></Cell><Cell ss:StyleID="s22"><Data ss:Type="String">1.320</Data></Cell><Cell ss:StyleID="s22"><Data ss:Type="String">1.771**</Data></Cell></Row><Row><Cell ss:StyleID="s32"><Data ss:Type="String"></Data></Cell><Cell ss:StyleID="s22"><Data ss:Type="String">[1.267]</Data></Cell><Cell ss:StyleID="s22"><Data ss:Type="String">[1.293]</Data></Cell><Cell ss:StyleID="s22"><Data ss:Type="String">[1.298]</Data></Cell><Cell ss:StyleID="s22"><Data ss:Type="String">[0.805]</Data></Cell><Cell ss:StyleID="s22"><Data ss:Type="String">[0.798]</Data></Cell><Cell ss:StyleID="s22"><Data ss:Type="String">[0.801]</Data></Cell><Cell ss:StyleID="s22"><Data ss:Type="String">[0.923]</Data></Cell><Cell ss:StyleID="s22"><Data ss:Type="String">[0.937]</Data></Cell><Cell ss:StyleID="s22"><Data ss:Type="String">[0.856]</Data></Cell><Cell ss:StyleID="s22"><Data ss:Type="String">[0.879]</Data></Cell></Row><Row><Cell ss:StyleID="s32"><Data ss:Type="String">Male</Data></Cell><Cell ss:StyleID="s22"><Data ss:Type="String">11.319***</Data></Cell><Cell ss:StyleID="s22"><Data ss:Type="String">11.320***</Data></Cell><Cell ss:StyleID="s22"><Data ss:Type="String">11.292***</Data></Cell><Cell ss:StyleID="s22"><Data ss:Type="String">12.323***</Data></Cell><Cell ss:StyleID="s22"><Data ss:Type="String">12.528***</Data></Cell><Cell ss:StyleID="s22"><Data ss:Type="String">12.397***</Data></Cell><Cell ss:StyleID="s22"><Data ss:Type="String">11.627***</Data></Cell><Cell ss:StyleID="s22"><Data ss:Type="String">12.128***</Data></Cell><Cell ss:StyleID="s22"><Data ss:Type="String">12.512***</Data></Cell><Cell ss:StyleID="s22"><Data ss:Type="String">12.775***</Data></Cell></Row><Row><Cell ss:StyleID="s32"><Data ss:Type="String"></Data></Cell><Cell ss:StyleID="s22"><Data ss:Type="String">[0.818]</Data></Cell><Cell ss:StyleID="s22"><Data ss:Type="String">[0.834]</Data></Cell><Cell ss:StyleID="s22"><Data ss:Type="String">[0.832]</Data></Cell><Cell ss:StyleID="s22"><Data ss:Type="String">[0.521]</Data></Cell><Cell ss:StyleID="s22"><Data ss:Type="String">[0.550]</Data></Cell><Cell ss:StyleID="s22"><Data ss:Type="String">[0.518]</Data></Cell><Cell ss:StyleID="s22"><Data ss:Type="String">[0.593]</Data></Cell><Cell ss:StyleID="s22"><Data ss:Type="String">[0.619]</Data></Cell><Cell ss:StyleID="s22"><Data ss:Type="String">[0.569]</Data></Cell><Cell ss:StyleID="s22"><Data ss:Type="String">[0.604]</Data></Cell></Row><Row><Cell ss:StyleID="s32"><Data ss:Type="String">poorBHealth</Data></Cell><Cell ss:StyleID="s22"><Data ss:Type="String">0.215</Data></Cell><Cell ss:StyleID="s22"><Data ss:Type="String">0.219</Data></Cell><Cell ss:StyleID="s22"><Data ss:Type="String">0.331</Data></Cell><Cell ss:StyleID="s22"><Data ss:Type="String">-0.879</Data></Cell><Cell ss:StyleID="s22"><Data ss:Type="String">-0.426</Data></Cell><Cell ss:StyleID="s22"><Data ss:Type="String">-0.986</Data></Cell><Cell ss:StyleID="s22"><Data ss:Type="String">0.102</Data></Cell><Cell ss:StyleID="s22"><Data ss:Type="String">0.631</Data></Cell><Cell ss:StyleID="s22"><Data ss:Type="String">-0.975</Data></Cell><Cell ss:StyleID="s22"><Data ss:Type="String">-0.494</Data></Cell></Row><Row><Cell ss:StyleID="s32"><Data ss:Type="String"></Data></Cell><Cell ss:StyleID="s22"><Data ss:Type="String">[1.807]</Data></Cell><Cell ss:StyleID="s22"><Data ss:Type="String">[1.827]</Data></Cell><Cell ss:StyleID="s22"><Data ss:Type="String">[1.789]</Data></Cell><Cell ss:StyleID="s22"><Data ss:Type="String">[0.877]</Data></Cell><Cell ss:StyleID="s22"><Data ss:Type="String">[0.896]</Data></Cell><Cell ss:StyleID="s22"><Data ss:Type="String">[0.828]</Data></Cell><Cell ss:StyleID="s22"><Data ss:Type="String">[1.045]</Data></Cell><Cell ss:StyleID="s22"><Data ss:Type="String">[1.012]</Data></Cell><Cell ss:StyleID="s22"><Data ss:Type="String">[1.124]</Data></Cell><Cell ss:StyleID="s22"><Data ss:Type="String">[1.143]</Data></Cell></Row><Row><Cell ss:StyleID="s32"><Data ss:Type="String">oldsibs</Data></Cell><Cell ss:StyleID="s22"><Data ss:Type="String">0.056</Data></Cell><Cell ss:StyleID="s22"><Data ss:Type="String">0.056</Data></Cell><Cell ss:StyleID="s22"><Data ss:Type="String">0.069</Data></Cell><Cell ss:StyleID="s22"><Data ss:Type="String">0.506</Data></Cell><Cell ss:StyleID="s22"><Data ss:Type="String">1.015*</Data></Cell><Cell ss:StyleID="s22"><Data ss:Type="String">0.550</Data></Cell><Cell ss:StyleID="s22"><Data ss:Type="String">0.513</Data></Cell><Cell ss:StyleID="s22"><Data ss:Type="String">0.825</Data></Cell><Cell ss:StyleID="s22"><Data ss:Type="String">0.133</Data></Cell><Cell ss:StyleID="s22"><Data ss:Type="String">0.204</Data></Cell></Row><Row><Cell ss:StyleID="s32"><Data ss:Type="String"></Data></Cell><Cell ss:StyleID="s22"><Data ss:Type="String">[0.856]</Data></Cell><Cell ss:StyleID="s22"><Data ss:Type="String">[0.855]</Data></Cell><Cell ss:StyleID="s22"><Data ss:Type="String">[0.854]</Data></Cell><Cell ss:StyleID="s22"><Data ss:Type="String">[0.568]</Data></Cell><Cell ss:StyleID="s22"><Data ss:Type="String">[0.571]</Data></Cell><Cell ss:StyleID="s22"><Data ss:Type="String">[0.560]</Data></Cell><Cell ss:StyleID="s22"><Data ss:Type="String">[0.657]</Data></Cell><Cell ss:StyleID="s22"><Data ss:Type="String">[0.682]</Data></Cell><Cell ss:StyleID="s22"><Data ss:Type="String">[0.602]</Data></Cell><Cell ss:StyleID="s22"><Data ss:Type="String">[0.608]</Data></Cell></Row><Row><Cell ss:StyleID="s32"><Data ss:Type="String">momMaxEdu_Uni_F</Data></Cell><Cell ss:StyleID="s22"><Data ss:Type="String">1.329</Data></Cell><Cell ss:StyleID="s22"><Data ss:Type="String">1.334</Data></Cell><Cell ss:StyleID="s22"><Data ss:Type="String">1.471</Data></Cell><Cell ss:StyleID="s22"><Data ss:Type="String">-0.474</Data></Cell><Cell ss:StyleID="s22"><Data ss:Type="String">-0.492</Data></Cell><Cell ss:StyleID="s22"><Data ss:Type="String">-0.503</Data></Cell><Cell ss:StyleID="s22"><Data ss:Type="String">1.182</Data></Cell><Cell ss:StyleID="s22"><Data ss:Type="String">1.252*</Data></Cell><Cell ss:StyleID="s22"><Data ss:Type="String">-0.303</Data></Cell><Cell ss:StyleID="s22"><Data ss:Type="String">-0.886</Data></Cell></Row><Row><Cell ss:StyleID="s32"><Data ss:Type="String"></Data></Cell><Cell ss:StyleID="s22"><Data ss:Type="String">[1.107]</Data></Cell><Cell ss:StyleID="s22"><Data ss:Type="String">[1.176]</Data></Cell><Cell ss:StyleID="s22"><Data ss:Type="String">[1.162]</Data></Cell><Cell ss:StyleID="s22"><Data ss:Type="String">[0.621]</Data></Cell><Cell ss:StyleID="s22"><Data ss:Type="String">[0.702]</Data></Cell><Cell ss:StyleID="s22"><Data ss:Type="String">[0.613]</Data></Cell><Cell ss:StyleID="s22"><Data ss:Type="String">[0.738]</Data></Cell><Cell ss:StyleID="s22"><Data ss:Type="String">[0.714]</Data></Cell><Cell ss:StyleID="s22"><Data ss:Type="String">[0.755]</Data></Cell><Cell ss:StyleID="s22"><Data ss:Type="String">[0.790]</Data></Cell></Row><Row><Cell ss:StyleID="s32"><Data ss:Type="String">dadMaxEdu_Uni_F</Data></Cell><Cell ss:StyleID="s22"><Data ss:Type="String">0.363</Data></Cell><Cell ss:StyleID="s22"><Data ss:Type="String">0.361</Data></Cell><Cell ss:StyleID="s22"><Data ss:Type="String">0.341</Data></Cell><Cell ss:StyleID="s22"><Data ss:Type="String">1.359**</Data></Cell><Cell ss:StyleID="s22"><Data ss:Type="String">0.771</Data></Cell><Cell ss:StyleID="s22"><Data ss:Type="String">1.383**</Data></Cell><Cell ss:StyleID="s22"><Data ss:Type="String">0.751</Data></Cell><Cell ss:StyleID="s22"><Data ss:Type="String">-0.096</Data></Cell><Cell ss:StyleID="s22"><Data ss:Type="String">0.942</Data></Cell><Cell ss:StyleID="s22"><Data ss:Type="String">0.794</Data></Cell></Row><Row><Cell ss:StyleID="s32"><Data ss:Type="String"></Data></Cell><Cell ss:StyleID="s22"><Data ss:Type="String">[1.218]</Data></Cell><Cell ss:StyleID="s22"><Data ss:Type="String">[1.221]</Data></Cell><Cell ss:StyleID="s22"><Data ss:Type="String">[1.221]</Data></Cell><Cell ss:StyleID="s22"><Data ss:Type="String">[0.654]</Data></Cell><Cell ss:StyleID="s22"><Data ss:Type="String">[0.745]</Data></Cell><Cell ss:StyleID="s22"><Data ss:Type="String">[0.650]</Data></Cell><Cell ss:StyleID="s22"><Data ss:Type="String">[0.803]</Data></Cell><Cell ss:StyleID="s22"><Data ss:Type="String">[0.822]</Data></Cell><Cell ss:StyleID="s22"><Data ss:Type="String">[0.799]</Data></Cell><Cell ss:StyleID="s22"><Data ss:Type="String">[0.817]</Data></Cell></Row><Row><Cell ss:StyleID="s32"><Data ss:Type="String">momMaxEdu_Uni_Miss</Data></Cell><Cell ss:StyleID="s22"><Data ss:Type="String">-0.231</Data></Cell><Cell ss:StyleID="s22"><Data ss:Type="String">-0.230</Data></Cell><Cell ss:StyleID="s22"><Data ss:Type="String">-0.355</Data></Cell><Cell ss:StyleID="s22"><Data ss:Type="String">0.006</Data></Cell><Cell ss:StyleID="s22"><Data ss:Type="String">-0.380</Data></Cell><Cell ss:StyleID="s22"><Data ss:Type="String">0.069</Data></Cell><Cell ss:StyleID="s22"><Data ss:Type="String">-0.626</Data></Cell><Cell ss:StyleID="s22"><Data ss:Type="String">-0.884</Data></Cell><Cell ss:StyleID="s22"><Data ss:Type="String">-0.151</Data></Cell><Cell ss:StyleID="s22"><Data ss:Type="String">-0.914</Data></Cell></Row><Row><Cell ss:StyleID="s32"><Data ss:Type="String"></Data></Cell><Cell ss:StyleID="s22"><Data ss:Type="String">[2.216]</Data></Cell><Cell ss:StyleID="s22"><Data ss:Type="String">[2.213]</Data></Cell><Cell ss:StyleID="s22"><Data ss:Type="String">[2.261]</Data></Cell><Cell ss:StyleID="s22"><Data ss:Type="String">[1.534]</Data></Cell><Cell ss:StyleID="s22"><Data ss:Type="String">[1.399]</Data></Cell><Cell ss:StyleID="s22"><Data ss:Type="String">[1.548]</Data></Cell><Cell ss:StyleID="s22"><Data ss:Type="String">[2.036]</Data></Cell><Cell ss:StyleID="s22"><Data ss:Type="String">[1.548]</Data></Cell><Cell ss:StyleID="s22"><Data ss:Type="String">[1.388]</Data></Cell><Cell ss:StyleID="s22"><Data ss:Type="String">[1.227]</Data></Cell></Row><Row><Cell ss:StyleID="s32"><Data ss:Type="String">dadMaxEdu_Uni_Miss</Data></Cell><Cell ss:StyleID="s22"><Data ss:Type="String">0.066</Data></Cell><Cell ss:StyleID="s22"><Data ss:Type="String">0.062</Data></Cell><Cell ss:StyleID="s22"><Data ss:Type="String">0.087</Data></Cell><Cell ss:StyleID="s22"><Data ss:Type="String">0.407</Data></Cell><Cell ss:StyleID="s22"><Data ss:Type="String">-0.809</Data></Cell><Cell ss:StyleID="s22"><Data ss:Type="String">0.489</Data></Cell><Cell ss:StyleID="s22"><Data ss:Type="String">-0.300</Data></Cell><Cell ss:StyleID="s22"><Data ss:Type="String">-1.161</Data></Cell><Cell ss:StyleID="s22"><Data ss:Type="String">1.008</Data></Cell><Cell ss:StyleID="s22"><Data ss:Type="String">0.734</Data></Cell></Row><Row><Cell ss:StyleID="s32"><Data ss:Type="String"></Data></Cell><Cell ss:StyleID="s22"><Data ss:Type="String">[1.141]</Data></Cell><Cell ss:StyleID="s22"><Data ss:Type="String">[1.200]</Data></Cell><Cell ss:StyleID="s22"><Data ss:Type="String">[1.214]</Data></Cell><Cell ss:StyleID="s22"><Data ss:Type="String">[0.821]</Data></Cell><Cell ss:StyleID="s22"><Data ss:Type="String">[0.848]</Data></Cell><Cell ss:StyleID="s22"><Data ss:Type="String">[0.824]</Data></Cell><Cell ss:StyleID="s22"><Data ss:Type="String">[0.839]</Data></Cell><Cell ss:StyleID="s22"><Data ss:Type="String">[0.904]</Data></Cell><Cell ss:StyleID="s22"><Data ss:Type="String">[0.901]</Data></Cell><Cell ss:StyleID="s22"><Data ss:Type="String">[0.957]</Data></Cell></Row><Row><Cell ss:StyleID="s32"><Data ss:Type="String">HighInc_F</Data></Cell><Cell ss:StyleID="s22"><Data ss:Type="String">-0.220</Data></Cell><Cell ss:StyleID="s22"><Data ss:Type="String">-0.223</Data></Cell><Cell ss:StyleID="s22"><Data ss:Type="String">-0.261</Data></Cell><Cell ss:StyleID="s22"><Data ss:Type="String">0.559</Data></Cell><Cell ss:StyleID="s22"><Data ss:Type="String">0.757</Data></Cell><Cell ss:StyleID="s22"><Data ss:Type="String">0.615</Data></Cell><Cell ss:StyleID="s22"><Data ss:Type="String">-0.169</Data></Cell><Cell ss:StyleID="s22"><Data ss:Type="String">0.197</Data></Cell><Cell ss:StyleID="s22"><Data ss:Type="String">0.423</Data></Cell><Cell ss:StyleID="s22"><Data ss:Type="String">0.385</Data></Cell></Row><Row><Cell ss:StyleID="s32"><Data ss:Type="String"></Data></Cell><Cell ss:StyleID="s22"><Data ss:Type="String">[1.028]</Data></Cell><Cell ss:StyleID="s22"><Data ss:Type="String">[1.076]</Data></Cell><Cell ss:StyleID="s22"><Data ss:Type="String">[1.087]</Data></Cell><Cell ss:StyleID="s22"><Data ss:Type="String">[0.717]</Data></Cell><Cell ss:StyleID="s22"><Data ss:Type="String">[0.746]</Data></Cell><Cell ss:StyleID="s22"><Data ss:Type="String">[0.710]</Data></Cell><Cell ss:StyleID="s22"><Data ss:Type="String">[0.771]</Data></Cell><Cell ss:StyleID="s22"><Data ss:Type="String">[0.807]</Data></Cell><Cell ss:StyleID="s22"><Data ss:Type="String">[0.790]</Data></Cell><Cell ss:StyleID="s22"><Data ss:Type="String">[0.798]</Data></Cell></Row><Row><Cell ss:StyleID="s32"><Data ss:Type="String">HighInc_Miss</Data></Cell><Cell ss:StyleID="s22"><Data ss:Type="String">-0.208</Data></Cell><Cell ss:StyleID="s22"><Data ss:Type="String">-0.210</Data></Cell><Cell ss:StyleID="s22"><Data ss:Type="String">-0.277</Data></Cell><Cell ss:StyleID="s22"><Data ss:Type="String">-0.516</Data></Cell><Cell ss:StyleID="s22"><Data ss:Type="String">-0.613</Data></Cell><Cell ss:StyleID="s22"><Data ss:Type="String">-0.538</Data></Cell><Cell ss:StyleID="s22"><Data ss:Type="String">-0.597</Data></Cell><Cell ss:StyleID="s22"><Data ss:Type="String">-0.504</Data></Cell><Cell ss:StyleID="s22"><Data ss:Type="String">-0.693</Data></Cell><Cell ss:StyleID="s22"><Data ss:Type="String">-0.934</Data></Cell></Row><Row><Cell ss:StyleID="s32"><Data ss:Type="String"></Data></Cell><Cell ss:StyleID="s22"><Data ss:Type="String">[1.098]</Data></Cell><Cell ss:StyleID="s22"><Data ss:Type="String">[1.123]</Data></Cell><Cell ss:StyleID="s22"><Data ss:Type="String">[1.144]</Data></Cell><Cell ss:StyleID="s22"><Data ss:Type="String">[0.648]</Data></Cell><Cell ss:StyleID="s22"><Data ss:Type="String">[0.662]</Data></Cell><Cell ss:StyleID="s22"><Data ss:Type="String">[0.644]</Data></Cell><Cell ss:StyleID="s22"><Data ss:Type="String">[0.780]</Data></Cell><Cell ss:StyleID="s22"><Data ss:Type="String">[0.808]</Data></Cell><Cell ss:StyleID="s22"><Data ss:Type="String">[0.697]</Data></Cell><Cell ss:StyleID="s22"><Data ss:Type="String">[0.707]</Data></Cell></Row><Row><Cell ss:StyleID="s32"><Data ss:Type="String">houseOwn_F</Data></Cell><Cell ss:StyleID="s22"><Data ss:Type="String">0.245</Data></Cell><Cell ss:StyleID="s22"><Data ss:Type="String">0.245</Data></Cell><Cell ss:StyleID="s22"><Data ss:Type="String">0.254</Data></Cell><Cell ss:StyleID="s22"><Data ss:Type="String">0.763</Data></Cell><Cell ss:StyleID="s22"><Data ss:Type="String">0.739</Data></Cell><Cell ss:StyleID="s22"><Data ss:Type="String">0.792</Data></Cell><Cell ss:StyleID="s22"><Data ss:Type="String">0.978</Data></Cell><Cell ss:StyleID="s22"><Data ss:Type="String">1.091</Data></Cell><Cell ss:StyleID="s22"><Data ss:Type="String">0.323</Data></Cell><Cell ss:StyleID="s22"><Data ss:Type="String">0.622</Data></Cell></Row><Row><Cell ss:StyleID="s32"><Data ss:Type="String"></Data></Cell><Cell ss:StyleID="s22"><Data ss:Type="String">[1.289]</Data></Cell><Cell ss:StyleID="s22"><Data ss:Type="String">[1.288]</Data></Cell><Cell ss:StyleID="s22"><Data ss:Type="String">[1.297]</Data></Cell><Cell ss:StyleID="s22"><Data ss:Type="String">[0.724]</Data></Cell><Cell ss:StyleID="s22"><Data ss:Type="String">[0.702]</Data></Cell><Cell ss:StyleID="s22"><Data ss:Type="String">[0.707]</Data></Cell><Cell ss:StyleID="s22"><Data ss:Type="String">[0.863]</Data></Cell><Cell ss:StyleID="s22"><Data ss:Type="String">[0.891]</Data></Cell><Cell ss:StyleID="s22"><Data ss:Type="String">[0.800]</Data></Cell><Cell ss:StyleID="s22"><Data ss:Type="String">[0.837]</Data></Cell></Row><Row><Cell ss:StyleID="s32"><Data ss:Type="String">distCenter</Data></Cell><Cell ss:StyleID="s22"><Data ss:Type="String">0.135</Data></Cell><Cell ss:StyleID="s22"><Data ss:Type="String">0.135</Data></Cell><Cell ss:StyleID="s22"><Data ss:Type="String">0.171</Data></Cell><Cell ss:StyleID="s22"><Data ss:Type="String">0.062</Data></Cell><Cell ss:StyleID="s22"><Data ss:Type="String">-0.040</Data></Cell><Cell ss:StyleID="s22"><Data ss:Type="String">0.055</Data></Cell><Cell ss:StyleID="s22"><Data ss:Type="String">0.118</Data></Cell><Cell ss:StyleID="s22"><Data ss:Type="String">0.076</Data></Cell><Cell ss:StyleID="s22"><Data ss:Type="String">0.127</Data></Cell><Cell ss:StyleID="s22"><Data ss:Type="String">0.116</Data></Cell></Row><Row><Cell ss:StyleID="s32"><Data ss:Type="String"></Data></Cell><Cell ss:StyleID="s22"><Data ss:Type="String">[0.166]</Data></Cell><Cell ss:StyleID="s22"><Data ss:Type="String">[0.167]</Data></Cell><Cell ss:StyleID="s22"><Data ss:Type="String">[0.176]</Data></Cell><Cell ss:StyleID="s22"><Data ss:Type="String">[0.153]</Data></Cell><Cell ss:StyleID="s22"><Data ss:Type="String">[0.161]</Data></Cell><Cell ss:StyleID="s22"><Data ss:Type="String">[0.157]</Data></Cell><Cell ss:StyleID="s22"><Data ss:Type="String">[0.140]</Data></Cell><Cell ss:StyleID="s22"><Data ss:Type="String">[0.151]</Data></Cell><Cell ss:StyleID="s22"><Data ss:Type="String">[0.137]</Data></Cell><Cell ss:StyleID="s22"><Data ss:Type="String">[0.152]</Data></Cell></Row><Row><Cell ss:StyleID="s32"><Data ss:Type="String">cgRelig_F</Data></Cell><Cell ss:StyleID="s22"><Data ss:Type="String">-0.407</Data></Cell><Cell ss:StyleID="s22"><Data ss:Type="String">-0.395</Data></Cell><Cell ss:StyleID="s22"><Data ss:Type="String">-0.606</Data></Cell><Cell ss:StyleID="s22"><Data ss:Type="String">0.926</Data></Cell><Cell ss:StyleID="s22"><Data ss:Type="String">1.277*</Data></Cell><Cell ss:StyleID="s22"><Data ss:Type="String">1.059</Data></Cell><Cell ss:StyleID="s22"><Data ss:Type="String">0.210</Data></Cell><Cell ss:StyleID="s22"><Data ss:Type="String">0.487</Data></Cell><Cell ss:StyleID="s22"><Data ss:Type="String">0.390</Data></Cell><Cell ss:StyleID="s22"><Data ss:Type="String">0.592</Data></Cell></Row><Row><Cell ss:StyleID="s32"><Data ss:Type="String"></Data></Cell><Cell ss:StyleID="s22"><Data ss:Type="String">[1.039]</Data></Cell><Cell ss:StyleID="s22"><Data ss:Type="String">[1.395]</Data></Cell><Cell ss:StyleID="s22"><Data ss:Type="String">[1.361]</Data></Cell><Cell ss:StyleID="s22"><Data ss:Type="String">[0.675]</Data></Cell><Cell ss:StyleID="s22"><Data ss:Type="String">[0.672]</Data></Cell><Cell ss:StyleID="s22"><Data ss:Type="String">[0.655]</Data></Cell><Cell ss:StyleID="s22"><Data ss:Type="String">[0.753]</Data></Cell><Cell ss:StyleID="s22"><Data ss:Type="String">[0.780]</Data></Cell><Cell ss:StyleID="s22"><Data ss:Type="String">[0.747]</Data></Cell><Cell ss:StyleID="s22"><Data ss:Type="String">[0.738]</Data></Cell></Row><Row><Cell ss:StyleID="s32"><Data ss:Type="String">o.cgRelig_Miss</Data></Cell><Cell ss:StyleID="s22"><Data ss:Type="String"></Data></Cell><Cell ss:StyleID="s22"><Data ss:Type="String"></Data></Cell><Cell ss:StyleID="s22"><Data ss:Type="String">-</Data></Cell><Cell ss:StyleID="s22"><Data ss:Type="String"></Data></Cell><Cell ss:StyleID="s22"><Data ss:Type="String">-</Data></Cell><Cell ss:StyleID="s22"><Data ss:Type="String"></Data></Cell><Cell ss:StyleID="s22"><Data ss:Type="String"></Data></Cell><Cell ss:StyleID="s22"><Data ss:Type="String">-</Data></Cell><Cell ss:StyleID="s22"><Data ss:Type="String"></Data></Cell><Cell ss:StyleID="s22"><Data ss:Type="String">-</Data></Cell></Row><Row><Cell ss:StyleID="s32"><Data ss:Type="String"></Data></Cell><Cell ss:StyleID="s22"><Data ss:Type="String"></Data></Cell><Cell ss:StyleID="s22"><Data ss:Type="String"></Data></Cell><Cell ss:StyleID="s22"><Data ss:Type="String"></Data></Cell><Cell ss:StyleID="s22"><Data ss:Type="String"></Data></Cell><Cell ss:StyleID="s22"><Data ss:Type="String"></Data></Cell><Cell ss:StyleID="s22"><Data ss:Type="String"></Data></Cell><Cell ss:StyleID="s22"><Data ss:Type="String"></Data></Cell><Cell ss:StyleID="s22"><Data ss:Type="String"></Data></Cell><Cell ss:StyleID="s22"><Data ss:Type="String"></Data></Cell><Cell ss:StyleID="s22"><Data ss:Type="String"></Data></Cell></Row><Row><Cell ss:StyleID="s32"><Data ss:Type="String">CAPI</Data></Cell><Cell ss:StyleID="s22"><Data ss:Type="String">-0.923</Data></Cell><Cell ss:StyleID="s22"><Data ss:Type="String">-0.928</Data></Cell><Cell ss:StyleID="s22"><Data ss:Type="String">-0.879</Data></Cell><Cell ss:StyleID="s22"><Data ss:Type="String">0.178</Data></Cell><Cell ss:StyleID="s22"><Data ss:Type="String">0.425</Data></Cell><Cell ss:StyleID="s22"><Data ss:Type="String">0.255</Data></Cell><Cell ss:StyleID="s22"><Data ss:Type="String">-0.159</Data></Cell><Cell ss:StyleID="s22"><Data ss:Type="String">0.099</Data></Cell><Cell ss:StyleID="s22"><Data ss:Type="String">0.036</Data></Cell><Cell ss:StyleID="s22"><Data ss:Type="String">0.656</Data></Cell></Row><Row><Cell ss:StyleID="s32"><Data ss:Type="String"></Data></Cell><Cell ss:StyleID="s22"><Data ss:Type="String">[0.829]</Data></Cell><Cell ss:StyleID="s22"><Data ss:Type="String">[0.975]</Data></Cell><Cell ss:StyleID="s22"><Data ss:Type="String">[0.971]</Data></Cell><Cell ss:StyleID="s22"><Data ss:Type="String">[0.541]</Data></Cell><Cell ss:StyleID="s22"><Data ss:Type="String">[0.559]</Data></Cell><Cell ss:StyleID="s22"><Data ss:Type="String">[0.537]</Data></Cell><Cell ss:StyleID="s22"><Data ss:Type="String">[0.629]</Data></Cell><Cell ss:StyleID="s22"><Data ss:Type="String">[0.649]</Data></Cell><Cell ss:StyleID="s22"><Data ss:Type="String">[0.586]</Data></Cell><Cell ss:StyleID="s22"><Data ss:Type="String">[0.616]</Data></Cell></Row><Row><Cell ss:StyleID="s32"><Data ss:Type="String">cgRelig_Miss</Data></Cell><Cell ss:StyleID="s22"><Data ss:Type="String">-2.292</Data></Cell><Cell ss:StyleID="s22"><Data ss:Type="String">-2.306</Data></Cell><Cell ss:StyleID="s22"><Data ss:Type="String"></Data></Cell><Cell ss:StyleID="s22"><Data ss:Type="String">2.372</Data></Cell><Cell ss:StyleID="s22"><Data ss:Type="String"></Data></Cell><Cell ss:StyleID="s22"><Data ss:Type="String">2.313</Data></Cell><Cell ss:StyleID="s22"><Data ss:Type="String">0.626</Data></Cell><Cell ss:StyleID="s22"><Data ss:Type="String"></Data></Cell><Cell ss:StyleID="s22"><Data ss:Type="String">1.568</Data></Cell><Cell ss:StyleID="s22"><Data ss:Type="String"></Data></Cell></Row><Row><Cell ss:StyleID="s32"><Data ss:Type="String"></Data></Cell><Cell ss:StyleID="s22"><Data ss:Type="String">[1.450]</Data></Cell><Cell ss:StyleID="s22"><Data ss:Type="String">[1.905]</Data></Cell><Cell ss:StyleID="s22"><Data ss:Type="String"></Data></Cell><Cell ss:StyleID="s22"><Data ss:Type="String">[1.631]</Data></Cell><Cell ss:StyleID="s22"><Data ss:Type="String"></Data></Cell><Cell ss:StyleID="s22"><Data ss:Type="String">[1.596]</Data></Cell><Cell ss:StyleID="s22"><Data ss:Type="String">[1.703]</Data></Cell><Cell ss:StyleID="s22"><Data ss:Type="String"></Data></Cell><Cell ss:StyleID="s22"><Data ss:Type="String">[1.695]</Data></Cell><Cell ss:StyleID="s22"><Data ss:Type="String"></Data></Cell></Row><Row><Cell ss:StyleID="s32"><Data ss:Type="String">Parma</Data></Cell><Cell ss:StyleID="s22"><Data ss:Type="String"></Data></Cell><Cell ss:StyleID="s22"><Data ss:Type="String"></Data></Cell><Cell ss:StyleID="s22"><Data ss:Type="String"></Data></Cell><Cell ss:StyleID="s22"><Data ss:Type="String"></Data></Cell><Cell ss:StyleID="s22"><Data ss:Type="String"></Data></Cell><Cell ss:StyleID="s22"><Data ss:Type="String"></Data></Cell><Cell ss:StyleID="s22"><Data ss:Type="String">0.240</Data></Cell><Cell ss:StyleID="s22"><Data ss:Type="String"></Data></Cell><Cell ss:StyleID="s22"><Data ss:Type="String"></Data></Cell><Cell ss:StyleID="s22"><Data ss:Type="String"></Data></Cell></Row><Row><Cell ss:StyleID="s32"><Data ss:Type="String"></Data></Cell><Cell ss:StyleID="s22"><Data ss:Type="String"></Data></Cell><Cell ss:StyleID="s22"><Data ss:Type="String"></Data></Cell><Cell ss:StyleID="s22"><Data ss:Type="String"></Data></Cell><Cell ss:StyleID="s22"><Data ss:Type="String"></Data></Cell><Cell ss:StyleID="s22"><Data ss:Type="String"></Data></Cell><Cell ss:StyleID="s22"><Data ss:Type="String"></Data></Cell><Cell ss:StyleID="s22"><Data ss:Type="String">[0.754]</Data></Cell><Cell ss:StyleID="s22"><Data ss:Type="String"></Data></Cell><Cell ss:StyleID="s22"><Data ss:Type="String"></Data></Cell><Cell ss:StyleID="s22"><Data ss:Type="String"></Data></Cell></Row><Row><Cell ss:StyleID="s32"><Data ss:Type="String">Reggio</Data></Cell><Cell ss:StyleID="s22"><Data ss:Type="String"></Data></Cell><Cell ss:StyleID="s22"><Data ss:Type="String"></Data></Cell><Cell ss:StyleID="s22"><Data ss:Type="String"></Data></Cell><Cell ss:StyleID="s22"><Data ss:Type="String"></Data></Cell><Cell ss:StyleID="s22"><Data ss:Type="String"></Data></Cell><Cell ss:StyleID="s22"><Data ss:Type="String"></Data></Cell><Cell ss:StyleID="s22"><Data ss:Type="String"></Data></Cell><Cell ss:StyleID="s22"><Data ss:Type="String">0.665</Data></Cell><Cell ss:StyleID="s22"><Data ss:Type="String"></Data></Cell><Cell ss:StyleID="s22"><Data ss:Type="String">-1.182</Data></Cell></Row><Row><Cell ss:StyleID="s32"><Data ss:Type="String"></Data></Cell><Cell ss:StyleID="s22"><Data ss:Type="String"></Data></Cell><Cell ss:StyleID="s22"><Data ss:Type="String"></Data></Cell><Cell ss:StyleID="s22"><Data ss:Type="String"></Data></Cell><Cell ss:StyleID="s22"><Data ss:Type="String"></Data></Cell><Cell ss:StyleID="s22"><Data ss:Type="String"></Data></Cell><Cell ss:StyleID="s22"><Data ss:Type="String"></Data></Cell><Cell ss:StyleID="s22"><Data ss:Type="String"></Data></Cell><Cell ss:StyleID="s22"><Data ss:Type="String">[0.950]</Data></Cell><Cell ss:StyleID="s22"><Data ss:Type="String"></Data></Cell><Cell ss:StyleID="s22"><Data ss:Type="String">[0.808]</Data></Cell></Row><Row><Cell ss:StyleID="s32"><Data ss:Type="String">materna_Municipal</Data></Cell><Cell ss:StyleID="s22"><Data ss:Type="String"></Data></Cell><Cell ss:StyleID="s22"><Data ss:Type="String"></Data></Cell><Cell ss:StyleID="s22"><Data ss:Type="String"></Data></Cell><Cell ss:StyleID="s22"><Data ss:Type="String"></Data></Cell><Cell ss:StyleID="s22"><Data ss:Type="String"></Data></Cell><Cell ss:StyleID="s22"><Data ss:Type="String"></Data></Cell><Cell ss:StyleID="s22"><Data ss:Type="String"></Data></Cell><Cell ss:StyleID="s22"><Data ss:Type="String">0.955</Data></Cell><Cell ss:StyleID="s22"><Data ss:Type="String"></Data></Cell><Cell ss:StyleID="s22"><Data ss:Type="String">-0.269</Data></Cell></Row><Row><Cell ss:StyleID="s32"><Data ss:Type="String"></Data></Cell><Cell ss:StyleID="s22"><Data ss:Type="String"></Data></Cell><Cell ss:StyleID="s22"><Data ss:Type="String"></Data></Cell><Cell ss:StyleID="s22"><Data ss:Type="String"></Data></Cell><Cell ss:StyleID="s22"><Data ss:Type="String"></Data></Cell><Cell ss:StyleID="s22"><Data ss:Type="String"></Data></Cell><Cell ss:StyleID="s22"><Data ss:Type="String"></Data></Cell><Cell ss:StyleID="s22"><Data ss:Type="String"></Data></Cell><Cell ss:StyleID="s22"><Data ss:Type="String">[0.874]</Data></Cell><Cell ss:StyleID="s22"><Data ss:Type="String"></Data></Cell><Cell ss:StyleID="s22"><Data ss:Type="String">[0.892]</Data></Cell></Row><Row><Cell ss:StyleID="s32"><Data ss:Type="String">Padova</Data></Cell><Cell ss:StyleID="s22"><Data ss:Type="String"></Data></Cell><Cell ss:StyleID="s22"><Data ss:Type="String"></Data></Cell><Cell ss:StyleID="s22"><Data ss:Type="String"></Data></Cell><Cell ss:StyleID="s22"><Data ss:Type="String"></Data></Cell><Cell ss:StyleID="s22"><Data ss:Type="String"></Data></Cell><Cell ss:StyleID="s22"><Data ss:Type="String"></Data></Cell><Cell ss:StyleID="s22"><Data ss:Type="String"></Data></Cell><Cell ss:StyleID="s22"><Data ss:Type="String"></Data></Cell><Cell ss:StyleID="s22"><Data ss:Type="String">1.153</Data></Cell><Cell ss:StyleID="s22"><Data ss:Type="String"></Data></Cell></Row><Row><Cell ss:StyleID="s32"><Data ss:Type="String"></Data></Cell><Cell ss:StyleID="s22"><Data ss:Type="String"></Data></Cell><Cell ss:StyleID="s22"><Data ss:Type="String"></Data></Cell><Cell ss:StyleID="s22"><Data ss:Type="String"></Data></Cell><Cell ss:StyleID="s22"><Data ss:Type="String"></Data></Cell><Cell ss:StyleID="s22"><Data ss:Type="String"></Data></Cell><Cell ss:StyleID="s22"><Data ss:Type="String"></Data></Cell><Cell ss:StyleID="s22"><Data ss:Type="String"></Data></Cell><Cell ss:StyleID="s22"><Data ss:Type="String"></Data></Cell><Cell ss:StyleID="s22"><Data ss:Type="String">[0.721]</Data></Cell><Cell ss:StyleID="s22"><Data ss:Type="String"></Data></Cell></Row><Row><Cell ss:StyleID="s32"><Data ss:Type="String">Constant</Data></Cell><Cell ss:StyleID="s22"><Data ss:Type="String">165.641***</Data></Cell><Cell ss:StyleID="s22"><Data ss:Type="String">165.543***</Data></Cell><Cell ss:StyleID="s22"><Data ss:Type="String">162.277***</Data></Cell><Cell ss:StyleID="s22"><Data ss:Type="String">145.484***</Data></Cell><Cell ss:StyleID="s22"><Data ss:Type="String">151.017***</Data></Cell><Cell ss:StyleID="s22"><Data ss:Type="String">143.473***</Data></Cell><Cell ss:StyleID="s22"><Data ss:Type="String">158.857***</Data></Cell><Cell ss:StyleID="s22"><Data ss:Type="String">155.707***</Data></Cell><Cell ss:StyleID="s22"><Data ss:Type="String">140.002***</Data></Cell><Cell ss:StyleID="s22"><Data ss:Type="String">132.224***</Data></Cell></Row><Row><Cell ss:StyleID="s32"><Data ss:Type="String"></Data></Cell><Cell ss:StyleID="s22"><Data ss:Type="String">[23.766]</Data></Cell><Cell ss:StyleID="s22"><Data ss:Type="String">[24.903]</Data></Cell><Cell ss:StyleID="s22"><Data ss:Type="String">[25.158]</Data></Cell><Cell ss:StyleID="s22"><Data ss:Type="String">[15.069]</Data></Cell><Cell ss:StyleID="s22"><Data ss:Type="String">[14.934]</Data></Cell><Cell ss:StyleID="s22"><Data ss:Type="String">[14.985]</Data></Cell><Cell ss:StyleID="s22"><Data ss:Type="String">[17.274]</Data></Cell><Cell ss:StyleID="s22"><Data ss:Type="String">[17.649]</Data></Cell><Cell ss:StyleID="s22"><Data ss:Type="String">[16.142]</Data></Cell><Cell ss:StyleID="s22"><Data ss:Type="String">[16.593]</Data></Cell></Row><Row><Cell ss:StyleID="s32"><Data ss:Type="String"></Data></Cell><Cell ss:StyleID="s22"><Data ss:Type="String"></Data></Cell><Cell ss:StyleID="s22"><Data ss:Type="String"></Data></Cell><Cell ss:StyleID="s22"><Data ss:Type="String"></Data></Cell><Cell ss:StyleID="s22"><Data ss:Type="String"></Data></Cell><Cell ss:StyleID="s22"><Data ss:Type="String"></Data></Cell><Cell ss:StyleID="s22"><Data ss:Type="String"></Data></Cell><Cell ss:StyleID="s22"><Data ss:Type="String"></Data></Cell><Cell ss:StyleID="s22"><Data ss:Type="String"></Data></Cell><Cell ss:StyleID="s22"><Data ss:Type="String"></Data></Cell><Cell ss:StyleID="s22"><Data ss:Type="String"></Data></Cell></Row><Row><Cell ss:StyleID="s32"><Data ss:Type="String">Observations</Data></Cell><Cell ss:StyleID="s22"><Data ss:Type="String">285</Data></Cell><Cell ss:StyleID="s22"><Data ss:Type="String">285</Data></Cell><Cell ss:StyleID="s22"><Data ss:Type="String">284</Data></Cell><Cell ss:StyleID="s22"><Data ss:Type="String">624</Data></Cell><Cell ss:StyleID="s22"><Data ss:Type="String">610</Data></Cell><Cell ss:StyleID="s22"><Data ss:Type="String">624</Data></Cell><Cell ss:StyleID="s22"><Data ss:Type="String">520</Data></Cell><Cell ss:StyleID="s22"><Data ss:Type="String">518</Data></Cell><Cell ss:StyleID="s22"><Data ss:Type="String">519</Data></Cell><Cell ss:StyleID="s22"><Data ss:Type="String">506</Data></Cell></Row><Row><Cell ss:StyleID="s32"><Data ss:Type="String">R-squared</Data></Cell><Cell ss:StyleID="s22"><Data ss:Type="String">0.425</Data></Cell><Cell ss:StyleID="s22"><Data ss:Type="String">0.425</Data></Cell><Cell ss:StyleID="s22"><Data ss:Type="String">0.427</Data></Cell><Cell ss:StyleID="s22"><Data ss:Type="String">0.481</Data></Cell><Cell ss:StyleID="s22"><Data ss:Type="String">0.506</Data></Cell><Cell ss:StyleID="s22"><Data ss:Type="String">0.487</Data></Cell><Cell ss:StyleID="s22"><Data ss:Type="String">0.436</Data></Cell><Cell ss:StyleID="s22"><Data ss:Type="String">0.467</Data></Cell><Cell ss:StyleID="s22"><Data ss:Type="String">0.498</Data></Cell><Cell ss:StyleID="s22"><Data ss:Type="String">0.520</Data></Cell></Row><Row><Cell ss:StyleID="s32"><Data ss:Type="String">Sample</Data></Cell><Cell ss:StyleID="s22"><Data ss:Type="String">Reggio</Data></Cell><Cell ss:StyleID="s22"><Data ss:Type="String">Reggio</Data></Cell><Cell ss:StyleID="s22"><Data ss:Type="String">Reggio</Data></Cell><Cell ss:StyleID="s22"><Data ss:Type="String">RAvsPrPd</Data></Cell><Cell ss:StyleID="s22"><Data ss:Type="String">RAvsPP</Data></Cell><Cell ss:StyleID="s22"><Data ss:Type="String">RAvsPP</Data></Cell><Cell ss:StyleID="s22"><Data ss:Type="String">RePr</Data></Cell><Cell ss:StyleID="s22"><Data ss:Type="String">RePr</Data></Cell><Cell ss:StyleID="s22"><Data ss:Type="String">RePd</Data></Cell><Cell ss:StyleID="s22"><Data ss:Type="String">RePd</Data></Cell></Row><Row><Cell ss:StyleID="s33"><Data ss:Type="String">Mean</Data></Cell><Cell ss:StyleID="s23"><Data ss:Type="String">170.86</Data></Cell><Cell ss:StyleID="s23"><Data ss:Type="String">170.86</Data></Cell><Cell ss:StyleID="s23"><Data ss:Type="String">170.86</Data></Cell><Cell ss:StyleID="s23"><Data ss:Type="String">170.86</Data></Cell><Cell ss:StyleID="s23"><Data ss:Type="String">170.86</Data></Cell><Cell ss:StyleID="s23"><Data ss:Type="String">170.86</Data></Cell><Cell ss:StyleID="s23"><Data ss:Type="String">170.86</Data></Cell><Cell ss:StyleID="s23"><Data ss:Type="String">170.86</Data></Cell><Cell ss:StyleID="s23"><Data ss:Type="String">170.86</Data></Cell><Cell ss:StyleID="s23"><Data ss:Type="String">170.86</Data></Cell></Row><Row><Cell ss:StyleID="s24"><Data ss:Type="String">Robust standard errors in brackets</Data></Cell></Row><Row><Cell ss:StyleID="s24"><Data ss:Type="String">*** p&lt;0.01, ** p&lt;0.05, * p&lt;0.1</Data></Cell></Row><Row><Cell ss:StyleID="s24"><Data ss:Type="String">Mean = average of the y-variable for the whole sample considered. Sample: Reggio = only respondents in the city of Reggio Emilia. RAvsPrPd = Reggio Approach and all the respondents in Parma and Padova. RePr= all of the respondents in Reggio Emilia and Parma. RePd= all of the respondents in Reggio Emilia and Padova. Estimation Procedure: OLS = Ordinary Least Square; IV = Instrumental variable approach; CF = control function approach</Data></Cell></Row><Row><Cell ss:StyleID="s24"><Data ss:Type="String">cubic polynomial or residuals. PSM = simple propensity score matching. PSM2 = propensity sore matching using both demand and supply. DiD = differences-in-differences approach</Data></Cell></Row><Row><Cell ss:StyleID="s24"><Data ss:Type="String">municipal schools vs other schools across different cities</Data></Cell></Row></Table><WorksheetOptions xmlns="urn:schemas-microsoft-com:office:excel"><ProtectedObjects>False</ProtectedObjects><ProtectedScenarios>False</ProtectedScenarios></WorksheetOptions></Worksheet></Workbook>